<?xml version="1.0"?>
<config xmlns:xsi="http://www.w3.org/2001/XMLSchema-instance" xsi:noNamespaceSchemaLocation="urn:magento:framework:Api/etc/extension_attributes.xsd">
    <extension_attributes for="Magento\InventoryApi\Api\Data\SourceInterface">

        <!-- colombia -->

        <attribute code="co_tipo_direccion" type="string"/>
        <attribute code="co_street2" type="string"/>
        <attribute code="co_street3" type="string"/>
        <attribute code="co_additional_info" type="string"/>
        <attribute code="co_ciudad" type="string"/>

        <!-- peru -->

        <attribute code="pe_distrito" type="string"/>
        <attribute code="pe_ciudad" type="string"/>

        <!-- costa rica -->

        <attribute code="cr_canton" type="string"/>
        <attribute code="cr_distrito" type="string"/>

    </extension_attributes>
    <extension_attributes for="Magento\Sales\Api\Data\OrderInterface">
        <attribute code="bopis" type="WolfSellers\Bopis\Api\Data\OrderBopisInterface" />
    </extension_attributes>
</config>
